spacy_to_naf/__init__.py
spacy_to_naf/converter.py
spacy_to_naf-0.2.0.dist-info/LICENSE
spacy_to_naf-0.2.0.dist-info/METADATA
spacy_to_naf-0.2.0.dist-info/WHEEL
spacy_to_naf-0.2.0.dist-info/top_level.txt
spacy_to_naf-0.2.0.dist-info/RECORD
