Metadata-Version: 2.1
Name: spacy-to-naf
Version: 0.2.0
Summary: spaCy-to-NAF converter
Author: Emiel van Miltenburg, Marten Postma, Sophie Arnoult
Author-email: s.i.arnoult@vu.nl
Maintainer: Sophie Arnoult
Maintainer-email: s.i.arnoult@vu.nl
License: Apache License 2.0
Project-URL: repository, https://github.com/cltl/Spacy_to_NAF
Project-URL: changelog, https://github.com/cltl/Spacy_to_NAF/blob/master/Changelog.md
Classifier: Programming Language :: Python :: 3
Classifier: Intended Audience :: Developers
Classifier: License :: OSI Approved :: Apache Software License
Requires-Python: >=3.7
License-File: LICENSE
Requires-Dist: nafparserpy
Requires-Dist: spacy
Provides-Extra: test
Requires-Dist: pytest ; extra == 'test'
